dbusapi/__init__.py
dbusapi/ast.py
dbusapi/interfaceparser.py
dbusapi/log.py
dbusapi/typeformatter.py
dbusapi/typeparser.py
dbusapi/types.py
dbusapi/tests/__init__.py
dbusapi/tests/test_ast.py
dbusapi/tests/test_interfaceparser.py
dbusapi/tests/test_typeformatter.py
dbusapi/tests/test_typeparser.py
dbusdeviation/__init__.py
dbusdeviation/interfacecomparator.py
dbusdeviation/tests/__init__.py
dbusdeviation/tests/test_interfacecomparator.py
dbusdeviation/utilities/__init__.py
dbusdeviation/utilities/diff.py
dbusdeviation/utilities/vcs_helper.py
dbus_deviation-0.6.1.dist-info/AUTHORS
dbus_deviation-0.6.1.dist-info/COPYING
dbus_deviation-0.6.1.dist-info/METADATA
dbus_deviation-0.6.1.dist-info/WHEEL
dbus_deviation-0.6.1.dist-info/entry_points.txt
dbus_deviation-0.6.1.dist-info/top_level.txt
dbus_deviation-0.6.1.dist-info/zip-safe
dbus_deviation-0.6.1.dist-info/RECORD
