Metadata-Version: 2.1
Name: dbus-deviation
Version: 0.6.1
Summary: Parse D-Bus introspection XML and process it in various ways
Home-page: https://tecnocode.co.uk/dbus-deviation/
Author: Philip Withnall
Author-email: philip@tecnocode.co.uk
License: LGPLv2.1+
Platform: UNKNOWN
Requires-Dist: lxml
